seqattn/__init__.py
seqattn/cache.py
seqattn/descriptor.py
seqattn-0.0.2.dist-info/licenses/LICENSE
seqattn-0.0.2.dist-info/METADATA
seqattn-0.0.2.dist-info/WHEEL
seqattn-0.0.2.dist-info/top_level.txt
seqattn-0.0.2.dist-info/RECORD
