Metadata-Version: 2.4
Name: seqattn
Version: 0.0.2
Summary: A convenient lib for sequence-level attention abstraction, powered by flashinfer
Author-email: Tomorrowdawn <tomorrowdawn@foxmail.com>
License-Expression: MIT
Project-URL: Homepage, https://github.com/Tomorrowdawn/seqattn
Project-URL: Repository, https://github.com/Tomorrowdawn/seqattn
Keywords: attention,llm,inference,kv-cache
Requires-Python: >=3.10
License-File: LICENSE
Requires-Dist: torch
Requires-Dist: numpy
Requires-Dist: attrs
Dynamic: license-file
